{
  "title": "Migrate",
  "is_top_level": true,
  "items": [
    {
      "title": "Overview",
      "urls": [
        "/molt/migration-overview.html"
      ]
    },
    {
      "title": "Migration Considerations",
      "items": [
        {
          "title": "Overview",
          "urls": [
            "/molt/migration-considerations.html"
          ]
        },
        {
          "title": "Migration Granularity",
          "urls": [
            "/molt/migration-considerations-granularity.html"
          ]
        },
        {
          "title": "Continuous Replication",
          "urls": [
            "/molt/migration-considerations-replication.html"
          ]
        },
        {
          "title": "Data Transformation Strategy",
          "urls": [
            "/molt/migration-considerations-transformation.html"
          ]
        },
        {
          "title": "Validation Strategy",
          "urls": [
            "/molt/migration-considerations-validation.html"
          ]
        },
        {
          "title": "Rollback Plan",
          "urls": [
            "/molt/migration-considerations-rollback.html"
          ]
        }
      ]
    },
    {
      "title": "MOLT Tools",
      "items": [
        {
          "title": "Schema Conversion Tool",
          "urls": [
            "/cockroachcloud/migrations-page.html"
          ]
        },
        {
          "title": "Fetch",
          "items": [
            {
              "title": "Guide",
              "urls": [
                "/molt/molt-fetch.html"
              ]
            },
            {
              "title": "Installation",
              "urls": [
                "/molt/molt-fetch-installation.html"
              ]
            },
            {
              "title": "Commands and Flags",
              "urls": [
                "/molt/molt-fetch-commands-and-flags.html"
              ]
            },
            {
              "title": "Metrics",
              "urls": [
                "/molt/molt-fetch-monitoring.html"
              ]
            },
            {
              "title": "Best Practices",
              "urls": [
                "/molt/molt-fetch-best-practices.html"
              ]
            },
            {
              "title": "Troubleshooting",
              "urls": [
                "/molt/molt-fetch-troubleshooting.html"
              ]
            }
          ]
        },
        {
          "title": "Replicator",
          "items": [
            {
              "title": "Guide",
              "urls": [
                "/molt/molt-replicator.html"
              ]
            },
            {
              "title": "Installation",
              "urls": [
                "/molt/molt-replicator-installation.html"
              ]
            },
            {
              "title": "Commands and Flags",
              "urls": [
                "/molt/replicator-flags.html"
              ]
            },
            {
              "title": "Userscripts",
              "items": [
                {
                  "title": "Overview",
                  "urls": [
                    "/molt/userscript-overview.html"
                  ]
                },
                {
                  "title": "Quickstart",
                  "urls": [
                    "/molt/userscript-quickstart.html"
                  ]
                },
                {
                  "title": "API",
                  "urls": [
                    "/molt/userscript-api.html"
                  ]
                },
                {
                  "title": "Cookbook",
                  "urls": [
                    "/molt/userscript-cookbook.html"
                  ]
                },
                {
                  "title": "Metrics",
                  "urls": [
                    "/molt/userscript-metrics.html"
                  ]
                }
              ]
            },
            {
              "title": "Metrics",
              "urls": [
                "/molt/replicator-metrics.html"
              ]
            },
            {
              "title": "Best Practices",
              "urls": [
                "/molt/molt-replicator-best-practices.html"
              ]
            },
            {
              "title": "Troubleshooting",
              "urls": [
                "/molt/molt-replicator-troubleshooting.html"
              ]
            }
          ]
        },
        {
          "title": "Verify",
          "urls": [
            "/molt/molt-verify.html"
          ]
        }
      ]
    },
    {
      "title": "Migration Strategy",
      "urls": [
        "/molt/migration-strategy.html"
      ]
    },
    {
      "title": "Common Migration Approaches",
      "items": [
        {
          "title": "Classic Bulk Load Migration",
          "items": [
            {
              "title": "Overview",
              "urls": [
                "/molt/migration-approach-classic-bulk-load.html"
              ]
            },
            {
              "title": "From PostgreSQL",
              "urls": [
                "/molt/classic-bulk-load-postgres.html"
              ]
            },
            {
              "title": "From MySQL",
              "urls": [
                "/molt/classic-bulk-load-mysql.html"
              ]
            },
            {
              "title": "From Oracle",
              "urls": [
                "/molt/classic-bulk-load-oracle.html"
              ]
            }
          ]
        },
        {
          "title": "Phased Bulk Load Migration",
          "items": [
            {
              "title": "Overview",
              "urls": [
                "/molt/migration-approach-phased-bulk-load.html"
              ]
            },
            {
              "title": "From PostgreSQL",
              "urls": [
                "/molt/phased-bulk-load-postgres.html"
              ]
            },
            {
              "title": "From MySQL",
              "urls": [
                "/molt/phased-bulk-load-mysql.html"
              ]
            },
            {
              "title": "From Oracle",
              "urls": [
                "/molt/phased-bulk-load-oracle.html"
              ]
            }
          ]
        },
        {
          "title": "Delta Migration",
          "items": [
            {
              "title": "Overview",
              "urls": [
                "/molt/migration-approach-delta.html"
              ]
            },
            {
              "title": "From PostgreSQL",
              "urls": [
                "/molt/delta-migration-postgres.html"
              ]
            },
            {
              "title": "From MySQL",
              "urls": [
                "/molt/delta-migration-mysql.html"
              ]
            },
            {
              "title": "From Oracle",
              "urls": [
                "/molt/delta-migration-oracle.html"
              ]
            }
          ]
        },
        {
          "title": "Phased Delta Migration with Failback Replication",
          "items": [
            {
              "title": "Overview",
              "urls": [
                "/molt/migration-approach-phased-delta-failback.html"
              ]
            },
            {
              "title": "From PostgreSQL",
              "urls": [
                "/molt/phased-delta-failback-postgres.html"
              ]
            },
            {
              "title": "From MySQL",
              "urls": [
                "/molt/phased-delta-failback-mysql.html"
              ]
            },
            {
              "title": "From Oracle",
              "urls": [
                "/molt/phased-delta-failback-oracle.html"
              ]
            }
          ]
        }
      ]
    },
    {
      "title": "Third-Party Migration Tools",
      "items": [
        {
          "title": "AWS DMS",
          "urls": [
            "/${VERSION}/aws-dms.html"
          ]
        },
        {
          "title": "Qlik Replicate",
          "urls": [
            "/${VERSION}/qlik.html"
          ]
        },
        {
          "title": "Striim",
          "urls": [
            "/${VERSION}/striim.html"
          ]
        },
        {
          "title": "Oracle GoldenGate",
          "urls": [
            "/${VERSION}/goldengate.html"
          ]
        },
        {
          "title": "Debezium",
          "urls": [
            "/${VERSION}/debezium.html"
          ]
        }
      ]
    },
    {
      "title": "Migrate Data Types",
      "items": [
        {
          "title": "Migrate from CSV",
          "urls": [
            "/${VERSION}/migrate-from-csv.html"
          ]
        },
        {
          "title": "Migrate from Avro",
          "urls": [
            "/${VERSION}/migrate-from-avro.html"
          ]
        },
        {
          "title": "Migrate from Shapefiles",
          "urls": [
            "/${VERSION}/migrate-from-shapefiles.html"
          ]
        },
        {
          "title": "Migrate from OpenStreetMap",
          "urls": [
            "/${VERSION}/migrate-from-openstreetmap.html"
          ]
        },
        {
          "title": "Migrate from GeoJSON",
          "urls": [
            "/${VERSION}/migrate-from-geojson.html"
          ]
        },
        {
          "title": "Migrate from GeoPackage",
          "urls": [
            "/${VERSION}/migrate-from-geopackage.html"
          ]
        },
        {
          "title": "Import Performance Best Practices",
          "urls": [
            "/${VERSION}/import-performance-best-practices.html"
          ]
        }
      ]
    }
  ]
}