{
  "width": 150,
  "title": null,
  "version": 1,
  "env": {
    "SHELL": "/bin/bash",
    "TERM": "xterm-256color"
  },
  "command": "/bin/bash -l",
  "duration": 131.531059,
  "height": 33,
  "stdout": [
    [
      0.031906,
      "\u001b[?1034h\u001b[32m~\u001b[m$ "
    ],
    [
      0.785576,
      "# Ste"
    ],
    [
      3.8e-05,
      "p 1. S"
    ],
    [
      0.00011,
      "tart t"
    ],
    [
      4.5e-05,
      "he f"
    ],
    [
      3.9e-05,
      "irs"
    ],
    [
      3.6e-05,
      "t "
    ],
    [
      4e-05,
      "n"
    ],
    [
      3.6e-05,
      "ode"
    ],
    [
      4.1e-05,
      "."
    ],
    [
      0.521098,
      "\r\n"
    ],
    [
      4.9e-05,
      "\u001b[32m~\u001b[m$ "
    ],
    [
      0.439044,
      "\r\n"
    ],
    [
      5.7e-05,
      "\u001b[32m~\u001b[m$ "
    ],
    [
      4.074014,
      "co"
    ],
    [
      3.8e-05,
      "ckroach s"
    ],
    [
      2.1e-05,
      "tar"
    ],
    [
      2.1e-05,
      "t "
    ],
    [
      2.9e-05,
      "--b"
    ],
    [
      2.3e-05,
      "ac"
    ],
    [
      1.9e-05,
      "kg"
    ],
    [
      1.8e-05,
      "ro"
    ],
    [
      1.9e-05,
      "un"
    ],
    [
      2e-05,
      "d"
    ],
    [
      0.594865,
      "\r\n"
    ],
    [
      0.215018,
      "CockroachDB node starting at 2017-04-07 10:25:15.083933992 -0400 EDT\r\nbuild:      CCL 764bcf0 @ 2017/04/05 22:45:58 (go1.8)\r\nadmin:      http://localhost:8080\r\nsql:        postgresql://root@localhost:26257?sslmode=disable\r\nlogs:       cockroach-data/logs\r\nstore[0]:   path=cockroach-data\r\nstatus:     initialized new cluster\r\nclusterID:  40ecce29-4b97-4e1f-a0e9-4cd2defcfc90\r\nnodeID:     1\r\n"
    ],
    [
      0.003271,
      "\u001b[32m~\u001b[m$ "
    ],
    [
      0.823407,
      "\r\n"
    ],
    [
      8.7e-05,
      "\u001b[32m~\u001b[m$ "
    ],
    [
      4.065808,
      "# Step 2."
    ],
    [
      9.3e-05,
      " Add n"
    ],
    [
      4.7e-05,
      "odes "
    ],
    [
      4.6e-05,
      "to"
    ],
    [
      4.6e-05,
      " th"
    ],
    [
      3.7e-05,
      "e "
    ],
    [
      2.5e-05,
      "cl"
    ],
    [
      2.4e-05,
      "us"
    ],
    [
      2.4e-05,
      "te"
    ],
    [
      2.4e-05,
      "r."
    ],
    [
      0.586049,
      "\r\n"
    ],
    [
      0.000157,
      "\u001b[32m~\u001b[m$ "
    ],
    [
      0.753481,
      "\r\n"
    ],
    [
      8.2e-05,
      "\u001b[32m~\u001b[m$ "
    ],
    [
      3.728016,
      "#"
    ],
    [
      6.6e-05,
      " Add th"
    ],
    [
      4.5e-05,
      "e secon"
    ],
    [
      1.9e-05,
      "d n"
    ],
    [
      2.2e-05,
      "od"
    ],
    [
      2.4e-05,
      "e"
    ],
    [
      1.9e-05,
      ":"
    ],
    [
      0.335986,
      "\r\n"
    ],
    [
      0.000136,
      "\u001b[32m~\u001b[m$ "
    ],
    [
      3.746133,
      "co"
    ],
    [
      5e-05,
      "ckroac"
    ],
    [
      3.8e-05,
      "h st"
    ],
    [
      3.6e-05,
      "ar"
    ],
    [
      3.7e-05,
      "t -"
    ],
    [
      3.5e-05,
      "-b"
    ],
    [
      3.3e-05,
      "ac"
    ],
    [
      3.6e-05,
      "kg"
    ],
    [
      5.2e-05,
      "rou"
    ],
    [
      4.3e-05,
      "nd"
    ],
    [
      2.1e-05,
      " -"
    ],
    [
      2.3e-05,
      "-"
    ],
    [
      2.2e-05,
      "st"
    ],
    [
      1.9e-05,
      "or"
    ],
    [
      2.1e-05,
      "e="
    ],
    [
      2e-05,
      "n"
    ],
    [
      2.1e-05,
      "od"
    ],
    [
      2.7e-05,
      "e"
    ],
    [
      2.1e-05,
      "2 "
    ],
    [
      2e-05,
      "-"
    ],
    [
      2e-05,
      "-p"
    ],
    [
      2.5e-05,
      "o"
    ],
    [
      2.1e-05,
      "r"
    ],
    [
      2.1e-05,
      "t="
    ],
    [
      2.3e-05,
      "2"
    ],
    [
      2.2e-05,
      "62"
    ],
    [
      2.5e-05,
      "5"
    ],
    [
      2.2e-05,
      "8"
    ],
    [
      2.1e-05,
      " -"
    ],
    [
      2e-05,
      "-"
    ],
    [
      2.1e-05,
      "h"
    ],
    [
      2.3e-05,
      "t"
    ],
    [
      2.1e-05,
      "t"
    ],
    [
      2.3e-05,
      "p"
    ],
    [
      2e-05,
      "-"
    ],
    [
      2.1e-05,
      "p"
    ],
    [
      2e-05,
      "or"
    ],
    [
      3.5e-05,
      "t"
    ],
    [
      2.3e-05,
      "="
    ],
    [
      2.1e-05,
      "80"
    ],
    [
      3.8e-05,
      "8"
    ],
    [
      3.8e-05,
      "1"
    ],
    [
      2e-05,
      " "
    ],
    [
      1.8e-05,
      "-"
    ],
    [
      1.9e-05,
      "-"
    ],
    [
      6.1e-05,
      "j"
    ],
    [
      3.9e-05,
      "oin"
    ],
    [
      2.8e-05,
      "="
    ],
    [
      2.6e-05,
      "lo"
    ],
    [
      4.1e-05,
      "c"
    ],
    [
      2.5e-05,
      "al"
    ],
    [
      3.3e-05,
      "h"
    ],
    [
      2.4e-05,
      "o"
    ],
    [
      2.3e-05,
      "s"
    ],
    [
      2.3e-05,
      "t"
    ],
    [
      2.2e-05,
      ":"
    ],
    [
      2e-05,
      "2"
    ],
    [
      2.2e-05,
      "6"
    ],
    [
      3.4e-05,
      "2"
    ],
    [
      2.3e-05,
      "5"
    ],
    [
      2.5e-05,
      "7"
    ],
    [
      0.468933,
      "\r\n"
    ],
    [
      0.183436,
      "CockroachDB node starting at 2017-04-07 10:25:29.78071084 -0400 EDT\r\nbuild:      CCL 764bcf0 @ 2017/04/05 22:45:58 (go1.8)\r\nadmin:      http://localhost:8081\r\nsql:        postgresql://root@localhost:26258?sslmode=disable\r\nlogs:       node2/logs\r\nstore[0]:   path=node2\r\nstatus:     initialized new node, joined pre-existing cluster\r\nclusterID:  40ecce29-4b97-4e1f-a0e9-4cd2defcfc90\r\nnodeID:     2\r\n"
    ],
    [
      0.004651,
      "\u001b[32m~\u001b[m$ "
    ],
    [
      0.917671,
      "\r\n"
    ],
    [
      0.000111,
      "\u001b[32m~\u001b[m$ "
    ],
    [
      7.3286,
      "# Add t"
    ],
    [
      9.3e-05,
      "he third"
    ],
    [
      6e-05,
      " no"
    ],
    [
      2.9e-05,
      "de:"
    ],
    [
      0.359346,
      "\r\n"
    ],
    [
      0.000151,
      "\u001b[32m~\u001b[m$ "
    ],
    [
      3.781407,
      "cockr"
    ],
    [
      5.4e-05,
      "oach s"
    ],
    [
      3.6e-05,
      "tar"
    ],
    [
      3.9e-05,
      "t -"
    ],
    [
      5.3e-05,
      "-ba"
    ],
    [
      3.7e-05,
      "ckg"
    ],
    [
      2.1e-05,
      "ro"
    ],
    [
      2.1e-05,
      "u"
    ],
    [
      2e-05,
      "nd"
    ],
    [
      2.2e-05,
      " -"
    ],
    [
      2.1e-05,
      "-s"
    ],
    [
      2e-05,
      "to"
    ],
    [
      2.2e-05,
      "r"
    ],
    [
      2e-05,
      "e="
    ],
    [
      2.3e-05,
      "no"
    ],
    [
      2.1e-05,
      "d"
    ],
    [
      2.4e-05,
      "e"
    ],
    [
      2.4e-05,
      "3 "
    ],
    [
      2.4e-05,
      "--"
    ],
    [
      2.3e-05,
      "p"
    ],
    [
      2.2e-05,
      "or"
    ],
    [
      2.4e-05,
      "t"
    ],
    [
      2.2e-05,
      "=2"
    ],
    [
      2.3e-05,
      "6"
    ],
    [
      2.2e-05,
      "25"
    ],
    [
      2.3e-05,
      "9"
    ],
    [
      2.2e-05,
      " -"
    ],
    [
      2.5e-05,
      "-"
    ],
    [
      2.1e-05,
      "h"
    ],
    [
      2.2e-05,
      "t"
    ],
    [
      2.2e-05,
      "tp"
    ],
    [
      2.3e-05,
      "-"
    ],
    [
      2.1e-05,
      "p"
    ],
    [
      2.3e-05,
      "o"
    ],
    [
      2.3e-05,
      "rt"
    ],
    [
      2.2e-05,
      "="
    ],
    [
      2.1e-05,
      "8"
    ],
    [
      2.3e-05,
      "0"
    ],
    [
      2.1e-05,
      "8"
    ],
    [
      2.2e-05,
      "2"
    ],
    [
      2.2e-05,
      " -"
    ],
    [
      6.8e-05,
      "-"
    ],
    [
      3.1e-05,
      "joi"
    ],
    [
      4.2e-05,
      "n"
    ],
    [
      2e-05,
      "="
    ],
    [
      2e-05,
      "l"
    ],
    [
      2e-05,
      "o"
    ],
    [
      1.9e-05,
      "c"
    ],
    [
      2e-05,
      "a"
    ],
    [
      3.4e-05,
      "l"
    ],
    [
      2.3e-05,
      "h"
    ],
    [
      2e-05,
      "o"
    ],
    [
      1.9e-05,
      "s"
    ],
    [
      3.3e-05,
      "t"
    ],
    [
      2.2e-05,
      ":"
    ],
    [
      1.9e-05,
      "2"
    ],
    [
      2e-05,
      "6"
    ],
    [
      3.4e-05,
      "2"
    ],
    [
      1.9e-05,
      "5"
    ],
    [
      2.1e-05,
      "7"
    ],
    [
      0.366846,
      "\r\n"
    ],
    [
      0.197092,
      "CockroachDB node starting at 2017-04-07 10:25:42.738590077 -0400 EDT\r\nbuild:      CCL 764bcf0 @ 2017/04/05 22:45:58 (go1.8)\r\nadmin:      http://localhost:8082\r\nsql:        postgresql://root@localhost:26259?sslmode=disable\r\nlogs:       node3/logs\r\nstore[0]:   path=node3\r\nstatus:     initialized new node, joined pre-existing cluster\r\nclusterID:  40ecce29-4b97-4e1f-a0e9-4cd2defcfc90\r\nnodeID:     3\r\n"
    ],
    [
      0.005503,
      "\u001b[32m~\u001b[m$ "
    ],
    [
      0.717864,
      "\r\n"
    ],
    [
      0.000126,
      "\u001b[32m~\u001b[m$ "
    ],
    [
      3.741663,
      "# "
    ],
    [
      3.9e-05,
      "Step 3. "
    ],
    [
      7.9e-05,
      "Tes"
    ],
    [
      2.6e-05,
      "t th"
    ],
    [
      2e-05,
      "e "
    ],
    [
      2.2e-05,
      "c"
    ],
    [
      4.6e-05,
      "lu"
    ],
    [
      1.9e-05,
      "st"
    ],
    [
      1.8e-05,
      "er"
    ],
    [
      1.9e-05,
      "."
    ],
    [
      0.304254,
      "\r\n"
    ],
    [
      0.000336,
      "\u001b[32m~\u001b[m$ "
    ],
    [
      0.546516,
      "\r\n"
    ],
    [
      0.000147,
      "\u001b[32m~\u001b[m$ "
    ],
    [
      3.823473,
      "# Start the built"
    ],
    [
      3.2e-05,
      "-in SQ"
    ],
    [
      1.9e-05,
      "L "
    ],
    [
      1.8e-05,
      "c"
    ],
    [
      2.4e-05,
      "li"
    ],
    [
      1.8e-05,
      "en"
    ],
    [
      1.8e-05,
      "t"
    ],
    [
      1.7e-05,
      " o"
    ],
    [
      1.8e-05,
      "n"
    ],
    [
      1.7e-05,
      " "
    ],
    [
      1.8e-05,
      "no"
    ],
    [
      0.000154,
      "de 1 and "
    ],
    [
      2.8e-05,
      "ex"
    ],
    [
      2e-05,
      "ec"
    ],
    [
      1.8e-05,
      "u"
    ],
    [
      1.8e-05,
      "t"
    ],
    [
      2.1e-05,
      "e"
    ],
    [
      1.8e-05,
      " "
    ],
    [
      2.2e-05,
      "st"
    ],
    [
      2.1e-05,
      "a"
    ],
    [
      1.8e-05,
      "t"
    ],
    [
      1.7e-05,
      "e"
    ],
    [
      2.2e-05,
      "m"
    ],
    [
      1.9e-05,
      "e"
    ],
    [
      1.8e-05,
      "n"
    ],
    [
      2.2e-05,
      "t"
    ],
    [
      2.3e-05,
      "s:"
    ],
    [
      0.327947,
      "\r\n"
    ],
    [
      0.000148,
      "\u001b[32m~\u001b[m$ "
    ],
    [
      4.7393,
      "co"
    ],
    [
      6.8e-05,
      "ckroach"
    ],
    [
      5.9e-05,
      " sql"
    ],
    [
      0.394344,
      "\r\n"
    ],
    [
      0.040675,
      "# Welcome to the cockroach SQL interface.\r\n# All statements must be terminated by a semicolon.\r\n# To exit: CTRL + D.\r\n"
    ],
    [
      0.000901,
      "\u001b[J\u001b[2K\rroot@:26257/>  \b"
    ],
    [
      4.979473,
      "\u001b[J\u001b[2K\rroot@:26257/> C"
    ],
    [
      6.6e-05,
      "\u001b[J\u001b[2K\rroot@:26257/> CR\u001b[J\u001b[2K\rroot@:26257/> CRE\u001b[J\u001b[2K\rroot@:26257/> CREA\u001b[J\u001b[2K\r"
    ],
    [
      5.4e-05,
      "root@:26257/> CREAT\u001b[J\u001b[2K\rroot@:26257/> CREATE\u001b[J\u001b[2K\r"
    ],
    [
      8.4e-05,
      "root@:26257/> CREATE \u001b[J\u001b[2K\rroot@:26257/> CREATE D\u001b[J\u001b[2K\r"
    ],
    [
      6.6e-05,
      "root@:26257/> CREATE DA\u001b[J\u001b[2K\rroot@:26257/> CREATE DAT\u001b[J\u001b[2K\rroot@:26257/> CREATE DATA\u001b[J\u001b[2K\r"
    ],
    [
      3.7e-05,
      "root@:26257/> CREATE DATAB\u001b[J\u001b[2K\rroot@:26257/> CREATE DATABA"
    ],
    [
      5e-05,
      "\u001b[J\u001b[2K\rroot@:26257/> CREATE DATABAS"
    ],
    [
      9e-05,
      "\u001b[J\u001b[2K\rroot@:26257/> CREATE DATABASE\u001b[J\u001b[2K\rroot@:26257/> CREATE DATABASE "
    ],
    [
      5.5e-05,
      "\u001b[J\u001b[2K\rroot@:26257/> CREATE DATABASE b\u001b[J\u001b[2K\rroot@:26257/> CREATE DATABASE ba"
    ],
    [
      4.3e-05,
      "\u001b[J\u001b[2K\rroot@:26257/> CREATE DATABASE ban\u001b[J\u001b[2K\r"
    ],
    [
      4e-05,
      "root@:26257/> CREATE DATABASE bank\u001b[J\u001b[2K\r"
    ],
    [
      4e-05,
      "root@:26257/> CREATE DATABASE bank;"
    ],
    [
      0.354285,
      "\u001b[J\u001b[2K\rroot@:26257/> CREATE DATABASE bank;\u001b[J\u001b[2K\rroot@:26257/> CREATE DATABASE bank;\r\n"
    ],
    [
      0.008047,
      "CREATE DATABASE\r\n"
    ],
    [
      0.000709,
      "\u001b[J\u001b[2K\rroot@:26257/>  \b"
    ],
    [
      5.14688,
      "\u001b[J\u001b[2K\rroot@:26257/> C"
    ],
    [
      6.1e-05,
      "\u001b[J\u001b[2K\rroot@:26257/> CR\u001b[J\u001b[2K\rroot@:26257/> CRE\u001b[J\u001b[2K\rroot@:26257/> CREA"
    ],
    [
      2.2e-05,
      "\u001b[J\u001b[2K\rroot@:26257/> CREAT"
    ],
    [
      2.1e-05,
      "\u001b[J\u001b[2K\rroot@:26257/> CREATE\u001b[J\u001b[2K\rroot@:26257/> CREATE "
    ],
    [
      2.1e-05,
      "\u001b[J\u001b[2K\rroot@:26257/> CREATE T\u001b[J\u001b[2K\r"
    ],
    [
      2.1e-05,
      "root@:26257/> CREATE TA\u001b[J\u001b[2K\rroot@:26257/> CREATE TAB"
    ],
    [
      2e-05,
      "\u001b[J\u001b[2K\rroot@:26257/> CREATE TABL"
    ],
    [
      2e-05,
      "\u001b[J\u001b[2K\r"
    ],
    [
      2.1e-05,
      "root@:26257/> CREATE TABLE\u001b[J\u001b[2K\rroot@:26257/> CREATE TABLE "
    ],
    [
      6.7e-05,
      "\u001b[J\u001b[2K\rroot@:26257/> CREATE TABLE b\u001b[J\u001b[2K\r"
    ],
    [
      2.4e-05,
      "root@:26257/> CREATE TABLE ba\u001b[J\u001b[2K\r"
    ],
    [
      1.9e-05,
      "root@:26257/> CREATE TABLE ban"
    ],
    [
      4.6e-05,
      "\u001b[J\u001b[2K\rroot@:26257/> CREATE TABLE bank"
    ],
    [
      2.9e-05,
      "\u001b[J\u001b[2K\rroot@:26257/> CREATE TABLE bank.\u001b[J\u001b[2K\r"
    ],
    [
      2e-05,
      "root@:26257/> CREATE TABLE bank.a\u001b[J\u001b[2K\rroot@:26257/> CREATE TABLE bank.ac"
    ],
    [
      6.1e-05,
      "\u001b[J\u001b[2K\rroot@:26257/> CREATE TABLE bank.acc"
    ],
    [
      4.2e-05,
      "\u001b[J\u001b[2K\rroot@:26257/> CREATE TABLE bank.acco\u001b[J\u001b[2K\rroot@:26257/> CREATE TABLE bank.accou"
    ],
    [
      3e-05,
      "\u001b[J\u001b[2K\rroot@:26257/> CREATE TABLE bank.accoun\u001b[J\u001b[2K\rroot@:26257/> CREATE TABLE bank.account"
    ],
    [
      2.7e-05,
      "\u001b[J\u001b[2K\rroot@:26257/> CREATE TABLE bank.accounts"
    ],
    [
      2.5e-05,
      "\u001b[J\u001b[2K\rroot@:26257/> CREATE TABLE bank.accounts "
    ],
    [
      7e-05,
      "\u001b[J\u001b[2K\rroot@:26257/> CREATE TABLE bank.accounts ("
    ],
    [
      2.9e-05,
      "\u001b[J\u001b[2K\rroot@:26257/> CREATE TABLE bank.accounts (i"
    ],
    [
      2.4e-05,
      "\u001b[J\u001b[2K\rroot@:26257/> CREATE TABLE bank.accounts (id"
    ],
    [
      2.1e-05,
      "\u001b[J\u001b[2K\rroot@:26257/> CREATE TABLE bank.accounts (id "
    ],
    [
      2.4e-05,
      "\u001b[J\u001b[2K\r"
    ],
    [
      2.2e-05,
      "root@:26257/> CREATE TABLE bank.accounts (id I\u001b[J\u001b[2K\r"
    ],
    [
      2.5e-05,
      "root@:26257/> CREATE TABLE bank.accounts (id IN"
    ],
    [
      2.3e-05,
      "\u001b[J\u001b[2K\rroot@:26257/> CREATE TABLE bank.accounts (id INT"
    ],
    [
      2.2e-05,
      "\u001b[J\u001b[2K\rroot@:26257/> CREATE TABLE bank.accounts (id INT "
    ],
    [
      2e-05,
      "\u001b[J\u001b[2K\r"
    ],
    [
      2.4e-05,
      "root@:26257/> CREATE TABLE bank.accounts (id INT P\u001b[J\u001b[2K\r"
    ],
    [
      2e-05,
      "root@:26257/> CREATE TABLE bank.accounts (id INT PR"
    ],
    [
      1.9e-05,
      "\u001b[J\u001b[2K\rroot@:26257/> CREATE TABLE bank.accounts (id INT PRI"
    ],
    [
      3e-05,
      "\u001b[J\u001b[2K\r"
    ],
    [
      2.2e-05,
      "root@:26257/> CREATE TABLE bank.accounts (id INT PRIM"
    ],
    [
      2.1e-05,
      "\u001b[J\u001b[2K\rroot@:26257/> CREATE TABLE bank.accounts (id INT PRIMA"
    ],
    [
      4.4e-05,
      "\u001b[J\u001b[2K\rroot@:26257/> CREATE TABLE bank.accounts (id INT PRIMAR"
    ],
    [
      3e-05,
      "\u001b[J\u001b[2K\rroot@:26257/> CREATE TABLE bank.accounts (id INT PRIMARY"
    ],
    [
      2.4e-05,
      "\u001b[J\u001b[2K\rroot@:26257/> CREATE TABLE bank.accounts (id INT PRIMARY "
    ],
    [
      2.1e-05,
      "\u001b[J\u001b[2K\r"
    ],
    [
      2.1e-05,
      "root@:26257/> CREATE TABLE bank.accounts (id INT PRIMARY K\u001b[J\u001b[2K\r"
    ],
    [
      2.3e-05,
      "root@:26257/> CREATE TABLE bank.accounts (id INT PRIMARY KE"
    ],
    [
      2.2e-05,
      "\u001b[J\u001b[2K\rroot@:26257/> CREATE TABLE bank.accounts (id INT PRIMARY KEY"
    ],
    [
      5.1e-05,
      "\u001b[J\u001b[2K\rroot@:26257/> CREATE TABLE bank.accounts (id INT PRIMARY KEY,"
    ],
    [
      2.2e-05,
      "\u001b[J\u001b[2K\r"
    ],
    [
      2.1e-05,
      "root@:26257/> CREATE TABLE bank.accounts (id INT PRIMARY KEY, "
    ],
    [
      2e-05,
      "\u001b[J\u001b[2K\rroot@:26257/> CREATE TABLE bank.accounts (id INT PRIMARY KEY, b"
    ],
    [
      4.7e-05,
      "\u001b[J\u001b[2K\rroot@:26257/> CREATE TABLE bank.accounts (id INT PRIMARY KEY, ba"
    ],
    [
      2.1e-05,
      "\u001b[J\u001b[2K\rroot@:26257/> CREATE TABLE bank.accounts (id INT PRIMARY KEY, bal"
    ],
    [
      3.8e-05,
      "\u001b[J\u001b[2K\r"
    ],
    [
      2.3e-05,
      "root@:26257/> CREATE TABLE bank.accounts (id INT PRIMARY KEY, bala\u001b[J\u001b[2K\r"
    ],
    [
      2.2e-05,
      "root@:26257/> CREATE TABLE bank.accounts (id INT PRIMARY KEY, balan"
    ],
    [
      4.8e-05,
      "\u001b[J\u001b[2K\rroot@:26257/> CREATE TABLE bank.accounts (id INT PRIMARY KEY, balanc"
    ],
    [
      2.8e-05,
      "\u001b[J\u001b[2K\rroot@:26257/> CREATE TABLE bank.accounts (id INT PRIMARY KEY, balance"
    ],
    [
      2.2e-05,
      "\u001b[J\u001b[2K\r"
    ],
    [
      2.2e-05,
      "root@:26257/> CREATE TABLE bank.accounts (id INT PRIMARY KEY, balance "
    ],
    [
      2.1e-05,
      "\u001b[J\u001b[2K\rroot@:26257/> CREATE TABLE bank.accounts (id INT PRIMARY KEY, balance D"
    ],
    [
      4.6e-05,
      "\u001b[J\u001b[2K\rroot@:26257/> CREATE TABLE bank.accounts (id INT PRIMARY KEY, balance DE"
    ],
    [
      2.3e-05,
      "\u001b[J\u001b[2K\r"
    ],
    [
      2e-05,
      "root@:26257/> CREATE TABLE bank.accounts (id INT PRIMARY KEY, balance DEC"
    ],
    [
      5.1e-05,
      "\u001b[J\u001b[2K\rroot@:26257/> CREATE TABLE bank.accounts (id INT PRIMARY KEY, balance DECI"
    ],
    [
      2.3e-05,
      "\u001b[J\u001b[2K\rroot@:26257/> CREATE TABLE bank.accounts (id INT PRIMARY KEY, balance DECIM"
    ],
    [
      6.8e-05,
      "\u001b[J\u001b[2K\r"
    ],
    [
      3.2e-05,
      "root@:26257/> CREATE TABLE bank.accounts (id INT PRIMARY KEY, balance DECIMA\u001b[J\u001b[2K\r"
    ],
    [
      2.1e-05,
      "root@:26257/> CREATE TABLE bank.accounts (id INT PRIMARY KEY, balance DECIMAL"
    ],
    [
      2e-05,
      "\u001b[J\u001b[2K\r"
    ],
    [
      2.7e-05,
      "root@:26257/> CREATE TABLE bank.accounts (id INT PRIMARY KEY, balance DECIMAL)"
    ],
    [
      1.9e-05,
      "\u001b[J\u001b[2K\r"
    ],
    [
      2.5e-05,
      "root@:26257/> CREATE TABLE bank.accounts (id INT PRIMARY KEY, balance DECIMAL);"
    ],
    [
      0.629195,
      "\u001b[J\u001b[2K\rroot@:26257/> CREATE TABLE bank.accounts (id INT PRIMARY KEY, balance DECIMAL);"
    ],
    [
      5.6e-05,
      "\u001b[J\u001b[2K\rroot@:26257/> CREATE TABLE bank.accounts (id INT PRIMARY KEY, balance DECIMAL);\r\n"
    ],
    [
      0.009248,
      "CREATE TABLE\r\n"
    ],
    [
      0.000843,
      "\u001b[J\u001b[2K\rroot@:26257/>  \b"
    ],
    [
      4.573451,
      "\u001b[J\u001b[2K\rroot@:26257/> I"
    ],
    [
      0.000112,
      "\u001b[J\u001b[2K\rroot@:26257/> IN\u001b[J\u001b[2K\rroot@:26257/> INS\u001b[J\u001b[2K\r"
    ],
    [
      5.7e-05,
      "root@:26257/> INSE\u001b[J\u001b[2K\rroot@:26257/> INSER\u001b[J\u001b[2K\rroot@:26257/> INSERT\u001b[J\u001b[2K\rroot@:26257/> INSERT "
    ],
    [
      2.4e-05,
      "\u001b[J\u001b[2K\rroot@:26257/> INSERT I\u001b[J\u001b[2K\r"
    ],
    [
      2.1e-05,
      "root@:26257/> INSERT IN\u001b[J\u001b[2K\r"
    ],
    [
      2.4e-05,
      "root@:26257/> INSERT INT"
    ],
    [
      2.1e-05,
      "\u001b[J\u001b[2K\rroot@:26257/> INSERT INTO"
    ],
    [
      2.1e-05,
      "\u001b[J\u001b[2K\rroot@:26257/> INSERT INTO \u001b[J\u001b[2K\r"
    ],
    [
      2.6e-05,
      "root@:26257/> INSERT INTO b\u001b[J\u001b[2K\r"
    ],
    [
      2.1e-05,
      "root@:26257/> INSERT INTO ba\u001b[J\u001b[2K\r"
    ],
    [
      2e-05,
      "root@:26257/> INSERT INTO ban\u001b[J\u001b[2K\r"
    ],
    [
      2e-05,
      "root@:26257/> INSERT INTO bank\u001b[J\u001b[2K\r"
    ],
    [
      1.9e-05,
      "root@:26257/> INSERT INTO bank."
    ],
    [
      2e-05,
      "\u001b[J\u001b[2K\rroot@:26257/> INSERT INTO bank.a"
    ],
    [
      0.000918,
      "\u001b[J\u001b[2K\rroot@:26257/> INSERT INTO bank.ac\u001b[J\u001b[2K\rroot@:26257/> INSERT INTO bank.acc\u001b[J\u001b[2K\rroot@:26257/> INSERT INTO bank.acco\u001b[J\u001b[2K\rroot@:26257/> INSERT INTO bank.accou\u001b[J\u001b[2K\rroot@:26257/> INSERT INTO bank.accoun\u001b[J\u001b[2K\rroot@:26257/> INSERT INTO bank.account\u001b[J\u001b[2K\rroot@:26257/> INSERT INTO bank.accounts\u001b[J\u001b[2K\rroot@:26257/> INSERT INTO bank.accounts \u001b[J\u001b[2K\rroot@:26257/> INSERT INTO bank.accounts V\u001b[J\u001b[2K\rroot@:26257/> INSERT INTO bank.accounts VA\u001b[J\u001b[2K\rroot@:26257/> INSERT INTO bank.accounts VAL\u001b[J\u001b[2K\rroot@:26257/> INSERT INTO bank.accounts VALU\u001b[J\u001b[2K\rroot@:26257/> INSERT INTO bank.accounts VALUE\u001b[J\u001b[2K\rroot@:26257/> INSERT INTO bank.accounts VALUES\u001b[J\u001b[2K\rroot@:26257/> INSERT INTO bank.accounts VALUES \u001b[J\u001b[2K\rroot@:26257/> INSERT INTO bank.accounts VALUES ("
    ],
    [
      3.1e-05,
      "\u001b[J\u001b[2K\rroot@:26257/> INSERT INTO bank.accounts VALUES (1"
    ],
    [
      9.6e-05,
      "\u001b[J\u001b[2K\rroot@:26257/> INSERT INTO bank.accounts VALUES (1,"
    ],
    [
      2.6e-05,
      "\u001b[J\u001b[2K\rroot@:26257/> INSERT INTO bank.accounts VALUES (1, "
    ],
    [
      2e-05,
      "\u001b[J\u001b[2K\r"
    ],
    [
      1.8e-05,
      "root@:26257/> INSERT INTO bank.accounts VALUES (1, 1"
    ],
    [
      2e-05,
      "\u001b[J\u001b[2K\rroot@:26257/> INSERT INTO bank.accounts VALUES (1, 10"
    ],
    [
      2.6e-05,
      "\u001b[J\u001b[2K\rroot@:26257/> INSERT INTO bank.accounts VALUES (1, 100"
    ],
    [
      2.1e-05,
      "\u001b[J\u001b[2K\rroot@:26257/> INSERT INTO bank.accounts VALUES (1, 1000"
    ],
    [
      1.8e-05,
      "\u001b[J\u001b[2K\r"
    ],
    [
      1.7e-05,
      "root@:26257/> INSERT INTO bank.accounts VALUES (1, 1000."
    ],
    [
      2.3e-05,
      "\u001b[J\u001b[2K\rroot@:26257/> INSERT INTO bank.accounts VALUES (1, 1000.5"
    ],
    [
      1.9e-05,
      "\u001b[J\u001b[2K\rroot@:26257/> INSERT INTO bank.accounts VALUES (1, 1000.50"
    ],
    [
      3.1e-05,
      "\u001b[J\u001b[2K\rroot@:26257/> INSERT INTO bank.accounts VALUES (1, 1000.50)"
    ],
    [
      2e-05,
      "\u001b[J\u001b[2K\r"
    ],
    [
      2.2e-05,
      "root@:26257/> INSERT INTO bank.accounts VALUES (1, 1000.50);"
    ],
    [
      1.009706,
      "\u001b[J\u001b[2K\rroot@:26257/> INSERT INTO bank.accounts VALUES (1, 1000.50);\u001b[J\u001b[2K\rroot@:26257/> INSERT INTO bank.accounts VALUES (1, 1000.50);\r\n"
    ],
    [
      0.010116,
      "INSERT 1\r\n"
    ],
    [
      0.000376,
      "\u001b[J\u001b[2K\rroot@:26257/>  \b"
    ],
    [
      4.489963,
      "\u001b[J\u001b[2K\rroot@:26257/> S\u001b[J\u001b[2K\r"
    ],
    [
      5.4e-05,
      "root@:26257/> SE\u001b[J\u001b[2K\rroot@:26257/> SEL\u001b[J\u001b[2K\r"
    ],
    [
      3.8e-05,
      "root@:26257/> SELE\u001b[J\u001b[2K\rroot@:26257/> SELEC"
    ],
    [
      3.4e-05,
      "\u001b[J\u001b[2K\rroot@:26257/> SELECT\u001b[J\u001b[2K\r"
    ],
    [
      4e-05,
      "root@:26257/> SELECT \u001b[J\u001b[2K\rroot@:26257/> SELECT *"
    ],
    [
      4.1e-05,
      "\u001b[J\u001b[2K\rroot@:26257/> SELECT * \u001b[J\u001b[2K\r"
    ],
    [
      2.5e-05,
      "root@:26257/> SELECT * F\u001b[J\u001b[2K\rroot@:26257/> SELECT * FR"
    ],
    [
      2.1e-05,
      "\u001b[J\u001b[2K\rroot@:26257/> SELECT * FRO\u001b[J\u001b[2K\r"
    ],
    [
      2.2e-05,
      "root@:26257/> SELECT * FROM\u001b[J\u001b[2K\r"
    ],
    [
      2.1e-05,
      "root@:26257/> SELECT * FROM \u001b[J\u001b[2K\rroot@:26257/> SELECT * FROM b"
    ],
    [
      2.2e-05,
      "\u001b[J\u001b[2K\rroot@:26257/> SELECT * FROM ba"
    ],
    [
      2.4e-05,
      "\u001b[J\u001b[2K\rroot@:26257/> SELECT * FROM ban\u001b[J\u001b[2K\r"
    ],
    [
      2.2e-05,
      "root@:26257/> SELECT * FROM bank"
    ],
    [
      2.2e-05,
      "\u001b[J\u001b[2K\rroot@:26257/> SELECT * FROM bank.\u001b[J\u001b[2K\r"
    ],
    [
      2.3e-05,
      "root@:26257/> SELECT * FROM bank.a\u001b[J\u001b[2K\r"
    ],
    [
      2.2e-05,
      "root@:26257/> SELECT * FROM bank.ac\u001b[J\u001b[2K\r"
    ],
    [
      2.2e-05,
      "root@:26257/> SELECT * FROM bank.acc\u001b[J\u001b[2K\r"
    ],
    [
      2.1e-05,
      "root@:26257/> SELECT * FROM bank.acco\u001b[J\u001b[2K\rroot@:26257/> SELECT * FROM bank.accou"
    ],
    [
      2.1e-05,
      "\u001b[J\u001b[2K\rroot@:26257/> SELECT * FROM bank.accoun"
    ],
    [
      2.4e-05,
      "\u001b[J\u001b[2K\rroot@:26257/> SELECT * FROM bank.account"
    ],
    [
      2.3e-05,
      "\u001b[J\u001b[2K\rroot@:26257/> SELECT * FROM bank.accounts"
    ],
    [
      2.4e-05,
      "\u001b[J\u001b[2K\rroot@:26257/> SELECT * FROM bank.accounts;"
    ],
    [
      0.735829,
      "\u001b[J\u001b[2K\rroot@:26257/> SELECT * FROM bank.accounts;\u001b[J\u001b[2K\rroot@:26257/> SELECT * FROM bank.accounts;\r\n"
    ],
    [
      0.004463,
      "+----+---------+\r\n| id | balance |\r\n+----+---------+\r\n| "
    ],
    [
      4.8e-05,
      " 1 | 1000.50 |\r\n+----+---------+\r\n(1 row)\r\n"
    ],
    [
      0.000695,
      "\u001b[J\u001b[2K\rroot@:26257/>  \b"
    ],
    [
      1.858893,
      "\u001b[J\u001b[2K\rroot@:26257/> \\"
    ],
    [
      0.07569,
      "\u001b[J\u001b[2K\rroot@:26257/> \\q"
    ],
    [
      0.151674,
      "\u001b[J\u001b[2K\rroot@:26257/> \\q\u001b[J\u001b[2K\rroot@:26257/> \\q\r\n"
    ],
    [
      5.6e-05,
      "\u001b[J\u001b[2K\r"
    ],
    [
      0.00325,
      "\u001b[32m~\u001b[m$ "
    ],
    [
      1.127797,
      "\r\n"
    ],
    [
      9.7e-05,
      "\u001b[32m~\u001b[m$ "
    ],
    [
      5.24383,
      "# S"
    ],
    [
      6.1e-05,
      "tart th"
    ],
    [
      3.4e-05,
      "e b"
    ],
    [
      3.1e-05,
      "ui"
    ],
    [
      4.6e-05,
      "lt-"
    ],
    [
      3.4e-05,
      "in"
    ],
    [
      2e-05,
      " S"
    ],
    [
      1.8e-05,
      "QL"
    ],
    [
      1.7e-05,
      " "
    ],
    [
      1.8e-05,
      "cl"
    ],
    [
      1.7e-05,
      "i"
    ],
    [
      1.7e-05,
      "en"
    ],
    [
      1.8e-05,
      "t"
    ],
    [
      1.8e-05,
      " o"
    ],
    [
      2.7e-05,
      "n "
    ],
    [
      1.8e-05,
      "n"
    ],
    [
      1.8e-05,
      "od"
    ],
    [
      1.8e-05,
      "e"
    ],
    [
      1.8e-05,
      " "
    ],
    [
      1.8e-05,
      "2"
    ],
    [
      1.7e-05,
      " a"
    ],
    [
      1.8e-05,
      "n"
    ],
    [
      2e-05,
      "d"
    ],
    [
      1.7e-05,
      " "
    ],
    [
      2.2e-05,
      "ru"
    ],
    [
      1.8e-05,
      "n"
    ],
    [
      1.7e-05,
      " "
    ],
    [
      1.7e-05,
      "t"
    ],
    [
      1.7e-05,
      "h"
    ],
    [
      1.7e-05,
      "e"
    ],
    [
      1.9e-05,
      " "
    ],
    [
      1.9e-05,
      "s"
    ],
    [
      1.7e-05,
      "a"
    ],
    [
      1.8e-05,
      "m"
    ],
    [
      1.8e-05,
      "e"
    ],
    [
      1.8e-05,
      " "
    ],
    [
      1.7e-05,
      "S"
    ],
    [
      1.8e-05,
      "E"
    ],
    [
      1.7e-05,
      "L"
    ],
    [
      1.9e-05,
      "E"
    ],
    [
      2.1e-05,
      "C"
    ],
    [
      2.1e-05,
      "T "
    ],
    [
      5.7e-05,
      "qu"
    ],
    [
      3.2e-05,
      "er"
    ],
    [
      2.3e-05,
      "y"
    ],
    [
      2.1e-05,
      ":"
    ],
    [
      0.554314,
      "\r\n"
    ],
    [
      0.000144,
      "\u001b[32m~\u001b[m$ "
    ],
    [
      7.410766,
      "c"
    ],
    [
      0.106649,
      "o"
    ],
    [
      0.144977,
      "c"
    ],
    [
      0.181142,
      "k"
    ],
    [
      0.121797,
      "r"
    ],
    [
      0.155145,
      "o"
    ],
    [
      0.189873,
      "a"
    ],
    [
      0.120968,
      "c"
    ],
    [
      0.100108,
      "h"
    ],
    [
      0.08695,
      " "
    ],
    [
      0.155972,
      "s"
    ],
    [
      0.167051,
      "q"
    ],
    [
      0.106979,
      "l"
    ],
    [
      0.083001,
      " "
    ],
    [
      0.870011,
      "-"
    ],
    [
      0.131947,
      "-"
    ],
    [
      0.626034,
      "p"
    ],
    [
      0.222093,
      "o"
    ],
    [
      0.164027,
      "r"
    ],
    [
      0.218852,
      "t"
    ],
    [
      0.994035,
      "="
    ],
    [
      0.641992,
      "2"
    ],
    [
      0.13592,
      "6"
    ],
    [
      0.121018,
      "2"
    ],
    [
      0.092093,
      "5"
    ],
    [
      0.334897,
      "8"
    ],
    [
      0.288967,
      "\r\n"
    ],
    [
      0.032201,
      "# Welcome to the cockroach SQL interface.\r\n# All statements must be terminated by a semicolon.\r\n# To exit: CTRL + D.\r\n"
    ],
    [
      0.000857,
      "\u001b[J\u001b[2K\rroot@:26258/>  \b"
    ],
    [
      2.262109,
      "\u001b[J\u001b[2K\rroot@:26258/> S"
    ],
    [
      6.3e-05,
      "\u001b[J\u001b[2K\rroot@:26258/> SE\u001b[J\u001b[2K\rroot@:26258/> SEL\u001b[J\u001b[2K\rroot@:26258/> SELE"
    ],
    [
      3.8e-05,
      "\u001b[J\u001b[2K\rroot@:26258/> SELEC"
    ],
    [
      8.6e-05,
      "\u001b[J\u001b[2K\rroot@:26258/> SELECT"
    ],
    [
      3.6e-05,
      "\u001b[J\u001b[2K\rroot@:26258/> SELECT "
    ],
    [
      6.6e-05,
      "\u001b[J\u001b[2K\rroot@:26258/> SELECT *"
    ],
    [
      6.8e-05,
      "\u001b[J\u001b[2K\rroot@:26258/> SELECT * "
    ],
    [
      3.7e-05,
      "\u001b[J\u001b[2K\rroot@:26258/> SELECT * F"
    ],
    [
      4.6e-05,
      "\u001b[J\u001b[2K\rroot@:26258/> SELECT * FR\u001b[J\u001b[2K\r"
    ],
    [
      4.6e-05,
      "root@:26258/> SELECT * FRO\u001b[J\u001b[2K\rroot@:26258/> SELECT * FROM"
    ],
    [
      3.6e-05,
      "\u001b[J\u001b[2K\rroot@:26258/> SELECT * FROM \u001b[J\u001b[2K\r"
    ],
    [
      3.6e-05,
      "root@:26258/> SELECT * FROM b\u001b[J\u001b[2K\rroot@:26258/> SELECT * FROM ba"
    ],
    [
      3.3e-05,
      "\u001b[J\u001b[2K\r"
    ],
    [
      3.5e-05,
      "root@:26258/> SELECT * FROM ban\u001b[J\u001b[2K\r"
    ],
    [
      3.4e-05,
      "root@:26258/> SELECT * FROM bank\u001b[J\u001b[2K\r"
    ],
    [
      3.5e-05,
      "root@:26258/> SELECT * FROM bank.\u001b[J\u001b[2K\rroot@:26258/> SELECT * FROM bank.a"
    ],
    [
      3.4e-05,
      "\u001b[J\u001b[2K\rroot@:26258/> SELECT * FROM bank.ac"
    ],
    [
      5.9e-05,
      "\u001b[J\u001b[2K\rroot@:26258/> SELECT * FROM bank.acc"
    ],
    [
      2.4e-05,
      "\u001b[J\u001b[2K\rroot@:26258/> SELECT * FROM bank.acco\u001b[J\u001b[2K\r"
    ],
    [
      2.1e-05,
      "root@:26258/> SELECT * FROM bank.accou\u001b[J\u001b[2K\r"
    ],
    [
      2.1e-05,
      "root@:26258/> SELECT * FROM bank.accoun"
    ],
    [
      2.1e-05,
      "\u001b[J\u001b[2K\rroot@:26258/> SELECT * FROM bank.account"
    ],
    [
      2e-05,
      "\u001b[J\u001b[2K\rroot@:26258/> SELECT * FROM bank.accounts"
    ],
    [
      8.2e-05,
      "\u001b[J\u001b[2K\rroot@:26258/> SELECT * FROM bank.accounts;"
    ],
    [
      0.412423,
      "\u001b[J\u001b[2K\rroot@:26258/> SELECT * FROM bank.accounts;\u001b[J\u001b[2K\rroot@:26258/> SELECT * FROM bank.accounts;\r\n"
    ],
    [
      0.009814,
      "+----+---------+\r\n| id | balance |\r\n+----+---------+\r\n| "
    ],
    [
      2.9e-05,
      " 1 | 1000.50 |\r\n+----+---------+\r\n(1 row)\r\n"
    ],
    [
      0.000422,
      "\u001b[J\u001b[2K\rroot@:26258/>  \b"
    ],
    [
      1.736517,
      "\u001b[J\u001b[2K\rroot@:26258/> \\"
    ],
    [
      0.156887,
      "\u001b[J\u001b[2K\rroot@:26258/> \\q"
    ],
    [
      0.232991,
      "\u001b[J\u001b[2K\rroot@:26258/> \\q"
    ],
    [
      4.8e-05,
      "\u001b[J\u001b[2K\rroot@:26258/> \\q\r\n"
    ],
    [
      0.000128,
      "\u001b[J\u001b[2K\r"
    ],
    [
      0.003433,
      "\u001b[32m~\u001b[m$ "
    ],
    [
      0.555258,
      "\r\n"
    ],
    [
      0.000223,
      "\u001b[32m~\u001b[m$ "
    ],
    [
      5.136599,
      "# S"
    ],
    [
      0.00012,
      "tep 4. When"
    ],
    [
      4.2e-05,
      " you'"
    ],
    [
      4e-05,
      "re"
    ],
    [
      4.5e-05,
      " f"
    ],
    [
      2.4e-05,
      "in"
    ],
    [
      2.3e-05,
      "is"
    ],
    [
      2.3e-05,
      "he"
    ],
    [
      2.4e-05,
      "d,"
    ],
    [
      2.1e-05,
      " s"
    ],
    [
      2.4e-05,
      "to"
    ],
    [
      2.2e-05,
      "p "
    ],
    [
      2.2e-05,
      "e"
    ],
    [
      2.4e-05,
      "ac"
    ],
    [
      2.2e-05,
      "h "
    ],
    [
      2.2e-05,
      "n"
    ],
    [
      2.2e-05,
      "od"
    ],
    [
      2.3e-05,
      "e"
    ],
    [
      4.7e-05,
      "."
    ],
    [
      0.603758,
      "\r\n"
    ],
    [
      0.000163,
      "\u001b[32m~\u001b[m$ "
    ],
    [
      1.410521,
      "\r\n"
    ],
    [
      0.000102,
      "\u001b[32m~\u001b[m$ "
    ],
    [
      3.874456,
      "coc"
    ],
    [
      3.9e-05,
      "kroach qu"
    ],
    [
      1.8e-05,
      "it"
    ],
    [
      0.407663,
      "\r\n"
    ],
    [
      0.048063,
      "initiating graceful shutdown of server\r\n"
    ],
    [
      0.005045,
      "ok\r\n"
    ],
    [
      0.001197,
      "server drained and shutdown completed\r\n"
    ],
    [
      0.002825,
      "\u001b[32m~\u001b[m$ "
    ],
    [
      4.953922,
      "\r\n"
    ],
    [
      8.5e-05,
      "\u001b[32m~\u001b[m$ "
    ],
    [
      0.581935,
      "co"
    ],
    [
      4.8e-05,
      "ckroach"
    ],
    [
      3.7e-05,
      " qu"
    ],
    [
      3.4e-05,
      "it "
    ],
    [
      3.5e-05,
      "--"
    ],
    [
      3.4e-05,
      "por"
    ],
    [
      3.4e-05,
      "t="
    ],
    [
      3.5e-05,
      "2"
    ],
    [
      0.000193,
      "6258"
    ],
    [
      0.432988,
      "\r\n"
    ],
    [
      0.046197,
      "initiating graceful shutdown of server\r\nok\r\n"
    ],
    [
      5.4e-05,
      "server drained and shutdown completed\r\n"
    ],
    [
      0.003774,
      "\u001b[32m~\u001b[m$ "
    ],
    [
      1.109014,
      "\r\n"
    ],
    [
      7.2e-05,
      "\u001b[32m~\u001b[m$ "
    ],
    [
      4.137569,
      "p"
    ],
    [
      5.3e-05,
      "s | gre"
    ],
    [
      3.8e-05,
      "p c"
    ],
    [
      4.4e-05,
      "ock"
    ],
    [
      3.5e-05,
      "ro"
    ],
    [
      3.9e-05,
      "ach"
    ],
    [
      0.591396,
      "\r\n"
    ],
    [
      0.010267,
      " 9297 ttys001    0:01.07 cockroach start --store=node3 --port=26259 --http-port=8082 --join=localhost:26257\r\n 9303 ttys001    0:00.00 grep cockroach\r\n"
    ],
    [
      0.00045,
      "\u001b[32m~\u001b[m$ "
    ],
    [
      1.64793,
      "\r\n"
    ],
    [
      0.000209,
      "\u001b[32m~\u001b[m$ "
    ],
    [
      0.656758,
      "k"
    ],
    [
      0.169919,
      "i"
    ],
    [
      0.191981,
      "l"
    ],
    [
      0.10999,
      "l"
    ],
    [
      0.45395,
      " "
    ],
    [
      0.492074,
      "-"
    ],
    [
      0.322081,
      "9"
    ],
    [
      0.197975,
      " "
    ],
    [
      4.09181,
      "929"
    ],
    [
      5.2e-05,
      "7"
    ],
    [
      0.520134,
      "\r\n"
    ],
    [
      0.000685,
      "\u001b[32m~\u001b[m$ "
    ]
  ]
}